wagtail_form_plugins/__init__.py
wagtail_form_plugins/locale/en/LC_MESSAGES/django.mo
wagtail_form_plugins/locale/en/LC_MESSAGES/django.po
wagtail_form_plugins/locale/fr/LC_MESSAGES/django.mo
wagtail_form_plugins/locale/fr/LC_MESSAGES/django.po
wagtail_form_plugins/migrations/0001_initial.py
wagtail_form_plugins/migrations/0002_validationtoken.py
wagtail_form_plugins/migrations/__init__.py
wagtail_form_plugins/plugins/__init__.py
wagtail_form_plugins/plugins/conditional_fields/__init__.py
wagtail_form_plugins/plugins/conditional_fields/blocks.py
wagtail_form_plugins/plugins/conditional_fields/dicts.py
wagtail_form_plugins/plugins/conditional_fields/form_field.py
wagtail_form_plugins/plugins/conditional_fields/models.py
wagtail_form_plugins/plugins/conditional_fields/utils.py
wagtail_form_plugins/plugins/editable/__init__.py
wagtail_form_plugins/plugins/editable/models.py
wagtail_form_plugins/plugins/editable/views.py
wagtail_form_plugins/plugins/emails/__init__.py
wagtail_form_plugins/plugins/emails/blocks.py
wagtail_form_plugins/plugins/emails/dicts.py
wagtail_form_plugins/plugins/emails/models.py
wagtail_form_plugins/plugins/file_input/__init__.py
wagtail_form_plugins/plugins/file_input/blocks.py
wagtail_form_plugins/plugins/file_input/form_field.py
wagtail_form_plugins/plugins/file_input/forms.py
wagtail_form_plugins/plugins/file_input/models.py
wagtail_form_plugins/plugins/file_input/views.py
wagtail_form_plugins/plugins/indexed_results/__init__.py
wagtail_form_plugins/plugins/indexed_results/models.py
wagtail_form_plugins/plugins/label/__init__.py
wagtail_form_plugins/plugins/label/blocks.py
wagtail_form_plugins/plugins/label/forms.py
wagtail_form_plugins/plugins/label/models.py
wagtail_form_plugins/plugins/label/views.py
wagtail_form_plugins/plugins/named_form/__init__.py
wagtail_form_plugins/plugins/named_form/models.py
wagtail_form_plugins/plugins/named_form/panels.py
wagtail_form_plugins/plugins/nav_buttons/__init__.py
wagtail_form_plugins-0.6.0.dist-info/licenses/LICENSE
wagtail_form_plugins-0.6.0.dist-info/WHEEL
wagtail_form_plugins-0.6.0.dist-info/METADATA
wagtail_form_plugins-0.6.0.dist-info/RECORD
