Metadata-Version: 2.4
Name: wagtail-form-plugins
Version: 0.6.0
Summary: A set of plugins used to customize and improve the Wagtail form builder in a modular way.
Keywords: wagtail,form,plugins
Author: Nathanaël Jourdane
Author-email: Nathanaël Jourdane <njourdane@laas.fr>
License-Expression: BSD-3-Clause
License-File: LICENSE
Classifier: Framework :: Wagtail
Requires-Dist: django
Requires-Dist: wagtail
Requires-Dist: django-bootstrap5 ; extra == 'demo'
Requires-Dist: wagtail-autocomplete ; extra == 'demo'
Requires-Python: >=3.10
Project-URL: homepage, https://pypi.org/project/wagtail_form_plugins
Project-URL: source, https://github.com/laas/wagtail-form-plugins
Project-URL: issues, https://github.com/laas/wagtail-form-plugins/issues
Provides-Extra: demo
